BerryDB.py
berrydb_sdk-1.0.1.dist-info/METADATA
berrydb_sdk-1.0.1.dist-info/WHEEL
berrydb_sdk-1.0.1.dist-info/top_level.txt
berrydb_sdk-1.0.1.dist-info/RECORD
