Metadata-Version: 2.1
Name: berrydb-sdk
Version: 1.0.1
Summary: Connect to your BerryDB database
Home-page: https://app.berrydb.io
Author: BerryDB
License: Proprietary
Classifier: License :: Other/Proprietary License
Requires-Dist: requests
